imem.v
module imem(
        output wire [15:0] rd,
        input [3:0] a);

    reg [15:0] ram [0:31];



    initial $readmemh("test1.txt", ram); 


    assign rd = ram[a];

endmodule

dmem.v
`timescale 1ns/1ps

module dmem(
        inout [7:0] data,
        input [3:0] addr,
        input we, clk, oe  
        );

    reg [7:0] ram [7:0];

    reg [7:0] tmp;
    integer i;
    always @ (posedge clk)
    begin
        if(we) begin
            ram[addr] <= data;
            #1
            $display("Checking if STUR works...");
            $display("this is ram[addr]: %d", ram[addr]);

        end
        else
            tmp <= data;
            #1
            $display("Checking if databus is working...");
            $display("this is tmp: %d", tmp);


    end
    assign data = oe & !we ? tmp : 'hz;

endmodule

datapath.v

// transfer data from ALU to dmem
module datapath(input [7:0] in, 
              input mux, clk,
              output reg [7:0] out);
    
    always @(*) begin
        if(mux)
            out <= in;
    end

endmodule

fullAdder.v
`ifndef FULL_ADDER
`define FULL_ADDER

module fullAdder(In1, In2, Cin, Sum, Cout);

    input In1, In2, Cin;
    output  Sum, Cout;
    
    assign Sum  = (In1 ^ In2) ^ Cin;
    assign Cout = (In1 & In2) | (In2 & Cin) | (Cin & In1);

endmodule

`endif // FULL_ADDER

adder8bit.v
`ifndef ADDER8BIT
`define ADDER8BIT


module adder8bit(In1, In2, Cin, Sum, Cout);

  input[7:0] In1, In2;
  input Cin;
  output[7:0] Sum;
  output Cout;
  wire [7:0] transferC;
  

  fullAdder FA1(.In1(In1[0]), .In2(In2[0]), .Cin(Cin), .Sum(Sum[0]), .Cout(transferC[0]));
  fullAdder FA2(.In1(In1[1]), .In2(In2[1]), .Cin(transferC[0]), .Sum(Sum[1]), .Cout(transferC[1]));
  fullAdder FA3(.In1(In1[2]), .In2(In2[2]), .Cin(transferC[1]), .Sum(Sum[2]), .Cout(transferC[2]));
  fullAdder FA4(.In1(In1[3]), .In2(In2[3]), .Cin(transferC[2]), .Sum(Sum[3]), .Cout(transferC[3]));
  fullAdder FA5(.In1(In1[4]), .In2(In2[4]), .Cin(transferC[3]), .Sum(Sum[4]), .Cout(transferC[4]));
  fullAdder FA6(.In1(In1[5]), .In2(In2[5]), .Cin(transferC[4]), .Sum(Sum[5]), .Cout(transferC[5]));
  fullAdder FA7(.In1(In1[6]), .In2(In2[6]), .Cin(transferC[5]), .Sum(Sum[6]), .Cout(transferC[6]));
  fullAdder FA8(.In1(In1[7]), .In2(In2[7]), .Cin(transferC[6]), .Sum(Sum[7]), .Cout(Cout));
endmodule

`endif

alu.v
module alu(
           input [7:0] A,B,                
           input [1:0] op,
           output [7:0] result,
           output COut 
    );
    reg [7:0] Y;
    assign result = Y; 
    assign COut = CarryOut;
    wire [15:0] mult;
    wire [7:0] Sum;
    wire CarryOut;
    assign mult = A*B;
    adder8bit adder(A, B, 1'b0, Sum, CarryOut); 
    
    always @(*)
    begin
        case(op)
          2'b00: begin // Addition
           Y <= Sum;
          //  if(CarryOut) begin
          //    $display("CarryOut GOT HERE");
          //  end 
          end
          2'b01: // MULT 
           Y <= mult[7:0];
          2'b10: //  AND 
           Y <= A & B;
          2'b11: //  Logical or
           Y <= A | B;
          default: Y = Sum; 
        endcase
    end
endmodule

cpu.v
`timescale 1ns/1ps

module cpu();

    reg [15:0] instruction;
    reg [7:0] A, B;
    reg [7:0] Rx [7:0];
    reg [1:0] alu_sel;
    reg [3:0] addr, pc;
    reg alu_mux, we, oe, clk;
    wire [15:0] instr;
    wire [7:0] bus;
    wire [3:0] Rn, Rd, Rm, opcode;
    wire COut;
    integer i;

    assign opcode = instruction[15:12];
    assign Rd = instruction[11:8];
    assign Rn = instruction[7:4];
    assign Rm = instruction[3:0];

    wire [7:0] tmp_alu;
    alu aluop(.A(A), .B(B), .result(tmp_alu), .op(alu_sel), .COut(COut));
    datapath dp(.clk(clk), .mux(alu_mux), .in(tmp_alu), .out(bus));
    dmem data(.data(bus), .clk(clk), .we(we), .oe(oe), .addr(addr));
    imem mem(.a(pc), .rd(instr));
    
    always @(posedge clk)
    begin
        case(opcode)
            4'b000:begin      // ADD
                A <= Rx[Rn];
                B <= Rx[Rm];
                alu_sel = 2'b00;
                alu_mux = 1'b1;
                #10
                Rx[Rd] = bus; 
                alu_mux = 1'b0;
            end
            4'b001:begin      // ADDI
                A <= Rx[Rn];
                B <= Rm;
                alu_sel = 2'b00;
                alu_mux = 1'b1;
                #10
                Rx[Rd] = bus;
                alu_mux = 1'b0;
            end
            4'b010: begin      //AND
                A <= Rx[Rn];
                B <= Rx[Rm];
                alu_sel = 2'b10;
                alu_mux = 1'b1;
                #10
                Rx[Rd] = bus;
                alu_mux = 1'b0;
            end
            4'b011: begin      //OR
                A <= Rx[Rn];
                B <= Rx[Rm];
                alu_sel = 2'b11;
                alu_mux = 1'b1;
                #10
                Rx[Rd] = bus;
                alu_mux = 1'b0;
            end
            4'b100:begin      // MULT
                A <= Rx[Rn];
                B <= Rx[Rm];
                alu_sel = 2'b01;
                alu_mux = 1'b1;
                #10
                Rx[Rd] = bus;
                alu_mux = 1'b0;
            end
            4'b101:begin      //Display
                $display("\nRegister Values\n");
                for(i =0; i < 8; i = i+1) begin
                    $display("Rx[%d]: %d",i, Rx[i]);
                end
            end
            4'b110:begin      //STUR 
                addr = Rd;
                A <= 0;
                B <= Rx[Rn];
                alu_sel = 2'b00;
                alu_mux = 1;
                oe = 0;
                we = 1;
                #10
                we = 0;
                alu_mux = 0;
            end
            4'b111:begin      //LDUR
                addr = Rd;
                we = 0;
                oe = 1;
                #10
                Rx[Rn] = bus;
                oe = 0;
            end
            4'b1001: begin
                $finish;    
            end

            default : A = 4'hz; 
        endcase
    end

    always @(negedge clk)
    begin
        pc = pc + 1;
        #10
        instruction = instr;
    end

    always #50 clk = ~clk;

    initial begin
        clk = 0;
        {we, oe, alu_mux, addr} <= 0;
        for(i = 0; i < 8; i = i+1) begin
            Rx[i] = 8'b0;
        end
        i = 0;
        pc = -1;
        #100
        $dumpfile("test.vcd");
        $dumpvars(0, clk, instruction, tmp_alu, Rx[0], Rx[1], Rx[2], Rx[3], Rx[4], Rx[5], Rx[6], Rx[7]);
        //$monitor("%d",Rx[1]);
        
    end
endmodule

test.vcd
$date
	Mon May 16 02:31:43 2022
$end
$version
	Icarus Verilog
$end
$timescale
	1ps
$end
$scope module cpu $end
$var reg 1 ! clk $end
$upscope $end
$scope module cpu $end
$var reg 16 " instruction [15:0] $end
$upscope $end
$scope module cpu $end
$var wire 8 # tmp_alu [7:0] $end
$upscope $end
$scope module cpu $end
$var reg 8 $ \Rx[0] [7:0] $end
$upscope $end
$scope module cpu $end
$var reg 8 % \Rx[1] [7:0] $end
$upscope $end
$scope module cpu $end
$var reg 8 & \Rx[2] [7:0] $end
$upscope $end
$scope module cpu $end
$var reg 8 ' \Rx[3] [7:0] $end
$upscope $end
$scope module cpu $end
$var reg 8 ( \Rx[4] [7:0] $end
$upscope $end
$scope module cpu $end
$var reg 8 ) \Rx[5] [7:0] $end
$upscope $end
$scope module cpu $end
$var reg 8 * \Rx[6] [7:0] $end
$upscope $end
$scope module cpu $end
$var reg 8 + \Rx[7] [7:0] $end
$upscope $end
$enddefinitions $end
#100000
$dumpvars
b0 +
b0 *
b0 )
b0 (
b0 '
b0 &
b0 %
b1 $
b1 #
b1000000000001 "
0!
$end
#110000
b1000100010010 "
#150000
b10 #
1!
#160000
b10 %
#200000
0!
#210000
b11001000000001 "
#250000
b11 #
1!
#260000
b11 &
#300000
0!
#310000
b10001100010010 "
#350000
b10 #
1!
#360000
b10 '
#400000
0!
#410000
b101000000000000 "
#450000
1!
#500000
0!
#510000
b1001000000000000 "
